udapi/__init__.py
udapi/block/__init__.py
udapi/block/corefud/__init__.py
udapi/block/corefud/bridgingclusters.py
udapi/block/corefud/concatmentionmisc.py
udapi/block/corefud/countgaps.py
udapi/block/corefud/delete.py
udapi/block/corefud/fixcorefud02.py
udapi/block/corefud/fixentityacrossnewdoc.py
udapi/block/corefud/fixinterleaved.py
udapi/block/corefud/fixparentheses.py
udapi/block/corefud/fixtovalidate.py
udapi/block/corefud/guessspan.py
udapi/block/corefud/gum2corefud.py
udapi/block/corefud/indexclusters.py
udapi/block/corefud/link2cluster.py
udapi/block/corefud/load.py
udapi/block/corefud/markcrossing.py
udapi/block/corefud/markinterleaved.py
udapi/block/corefud/marknested.py
udapi/block/corefud/markpairs.py
udapi/block/corefud/marksamesubspan.py
udapi/block/corefud/mergesamespan.py
udapi/block/corefud/miscstats.py
udapi/block/corefud/miscstatstex.py
udapi/block/corefud/movehead.py
udapi/block/corefud/printentities.py
udapi/block/corefud/printmentions.py
udapi/block/corefud/removemisc.py
udapi/block/corefud/removenocorefentities.py
udapi/block/corefud/singleparent.py
udapi/block/corefud/stats.py
udapi/block/demo/__init__.py
udapi/block/demo/complexity.py
udapi/block/demo/newspeak.py
udapi/block/demo/rehangprepositions.py
udapi/block/eval/__init__.py
udapi/block/eval/conll17.py
udapi/block/eval/conll18.py
udapi/block/eval/f1.py
udapi/block/eval/parsing.py
udapi/block/read/__init__.py
udapi/block/read/addsentences.py
udapi/block/read/addtext.py
udapi/block/read/ccv.py
udapi/block/read/conll.py
udapi/block/read/conll2012.py
udapi/block/read/conllu.py
udapi/block/read/conllup.py
udapi/block/read/oldcorefud.py
udapi/block/read/sentences.py
udapi/block/read/text.py
udapi/block/read/vislcg.py
udapi/block/tokenize/__init__.py
udapi/block/tokenize/onwhitespace.py
udapi/block/tokenize/simple.py
udapi/block/transform/__init__.py
udapi/block/transform/deproj.py
udapi/block/transform/flatten.py
udapi/block/transform/proj.py
udapi/block/tutorial/__init__.py
udapi-0.5.0.dist-info/licenses/LICENSE
udapi-0.5.0.dist-info/METADATA
udapi-0.5.0.dist-info/WHEEL
udapi-0.5.0.dist-info/top_level.txt
udapi-0.5.0.dist-info/RECORD
