Metadata-Version: 2.4
Name: udapi
Version: 0.5.0
Summary: Python framework for processing Universal Dependencies data
Home-page: https://github.com/udapi/udapi-python
Author: Martin Popel
Author-email: popel@ufal.mff.cuni.cz
Classifier: Programming Language :: Python :: 3
Classifier: License :: OSI Approved :: GNU General Public License v2 or later (GPLv2+)
Classifier: Operating System :: OS Independent
Requires-Python: >=3.9
License-File: LICENSE
Requires-Dist: colorama
Requires-Dist: termcolor
Provides-Extra: test
Requires-Dist: pytest; extra == "test"
Dynamic: license-file
